exiv2/_properties.cpython-313-darwin.so
exiv2/extras.py
exiv2/tags.py
exiv2/preview.py
exiv2/_version_module.cpython-313-darwin.so
exiv2/iptc.py
exiv2/_image.cpython-313-darwin.so
exiv2/error.py
exiv2/_xmp.cpython-313-darwin.so
exiv2/_tags.cpython-313-darwin.so
exiv2/properties.py
exiv2/_exif.cpython-313-darwin.so
exiv2/_iptc.cpython-313-darwin.so
exiv2/basicio.py
exiv2/datasets.py
exiv2/__init__.py
exiv2/_types.cpython-313-darwin.so
exiv2/types.py
exiv2/_enum_data.py
exiv2/xmp.py
exiv2/easyaccess.py
exiv2/_metadatum.cpython-313-darwin.so
exiv2/exif.py
exiv2/_value.cpython-313-darwin.so
exiv2/value.py
exiv2/metadatum_pointer.hpp
exiv2/_error.cpython-313-darwin.so
exiv2/_datasets.cpython-313-darwin.so
exiv2/version_module.py
exiv2/metadatum.py
exiv2/image.py
exiv2/__main__.py
exiv2/_preview.cpython-313-darwin.so
exiv2/_easyaccess.cpython-313-darwin.so
exiv2/_basicio.cpython-313-darwin.so
exiv2/locale/sk/LC_MESSAGES/exiv2.mo
exiv2/locale/ug/LC_MESSAGES/exiv2.mo
exiv2/locale/pl/LC_MESSAGES/exiv2.mo
exiv2/locale/vi/LC_MESSAGES/exiv2.mo
exiv2/locale/sv/LC_MESSAGES/exiv2.mo
exiv2/locale/ms/LC_MESSAGES/exiv2.mo
exiv2/locale/da/LC_MESSAGES/exiv2.mo
exiv2/locale/pt_BR/LC_MESSAGES/exiv2.mo
exiv2/locale/it/LC_MESSAGES/exiv2.mo
exiv2/locale/ca/LC_MESSAGES/exiv2.mo
exiv2/locale/ru/LC_MESSAGES/exiv2.mo
exiv2/locale/pt/LC_MESSAGES/exiv2.mo
exiv2/locale/uk/LC_MESSAGES/exiv2.mo
exiv2/locale/bs/LC_MESSAGES/exiv2.mo
exiv2/locale/gl/LC_MESSAGES/exiv2.mo
exiv2/locale/nl/LC_MESSAGES/exiv2.mo
exiv2/locale/ka/LC_MESSAGES/exiv2.mo
exiv2/locale/de/LC_MESSAGES/exiv2.mo
exiv2/locale/fi/LC_MESSAGES/exiv2.mo
exiv2/locale/fr/LC_MESSAGES/exiv2.mo
exiv2/locale/es/LC_MESSAGES/exiv2.mo
exiv2/.dylibs/libinih.0.dylib
exiv2/.dylibs/libINIReader.0.dylib
exiv2/.dylibs/libbrotlidec.1.1.0.dylib
exiv2/.dylibs/libbrotlicommon.1.1.0.dylib
exiv2/.dylibs/libintl.8.dylib
exiv2/examples/addmoddel.py
exiv2/examples/values.py
exiv2-0.18.0.dist-info/RECORD
exiv2-0.18.0.dist-info/WHEEL
exiv2-0.18.0.dist-info/top_level.txt
exiv2-0.18.0.dist-info/METADATA
exiv2-0.18.0.dist-info/licenses/LICENSE
