Metadata-Version: 2.1
Name: exiv2
Version: 0.18.0
Summary: Python interface to libexiv2
Author-email: Jim Easterbrook <jim@jim-easterbrook.me.uk>
License: GNU GPL
Project-URL: Homepage, https://github.com/jim-easterbrook/python-exiv2
Project-URL: Changelog, https://github.com/jim-easterbrook/python-exiv2/blob/main/CHANGELOG.txt
Project-URL: Documentation, https://python-exiv2.readthedocs.io/
Platform: POSIX
Platform: MacOS
Platform: Windows
Classifier: Development Status :: 4 - Beta
Classifier: Intended Audience :: Developers
Classifier: License :: OSI Approved :: GNU General Public License v3 or later (GPLv3+)
Classifier: Operating System :: MacOS
Classifier: Operating System :: MacOS :: MacOS X
Classifier: Operating System :: POSIX
Classifier: Operating System :: POSIX :: Linux
Classifier: Operating System :: Microsoft
Classifier: Operating System :: Microsoft :: Windows
Classifier: Programming Language :: Python :: 3
Classifier: Topic :: Multimedia
Classifier: Topic :: Multimedia :: Graphics
License-File: LICENSE
